{"namespace":"Sweep207DesignSystem_2038ab","components":[],"startingPoints":[],"cards":[{"path":"preview/brand-imagery.html","group":"Brand","viewport":"700x320","subtitle":"Real-home & on-the-job photography style","name":"Imagery"},{"path":"preview/brand-lockup.html","group":"Brand","viewport":"700x230","subtitle":"Badge + wordmark + clearspace","name":"Logo — Lockup"},{"path":"preview/brand-logo-badge.html","group":"Brand","viewport":"700x290","subtitle":"Primary, inverse & mono treatments","name":"Logo — Badge"},{"path":"preview/brand-logo-marks.html","group":"Brand","viewport":"700x230","subtitle":"Single-tone color treatments","name":"Logo — Mark Variants"},{"path":"preview/brand-motif.html","group":"Brand","viewport":"700x270","subtitle":"Soap-bubble overlay system","name":"Brand Motif"},{"path":"preview/color-accents.html","group":"Colors","viewport":"700x215","subtitle":"Highlight-only support colors","name":"Accents — Lime & Green"},{"path":"preview/color-neutrals.html","group":"Colors","viewport":"700x210","subtitle":"Teal-tinted paper, backgrounds & lines","name":"Neutrals"},{"path":"preview/color-primary.html","group":"Colors","viewport":"700x210","subtitle":"Brand action color, hover & tint","name":"Primary — Spring Teal"},{"path":"preview/color-scale.html","group":"Colors","viewport":"700x215","subtitle":"900 → 100 analogous ramp","name":"Teal Scale"},{"path":"preview/color-semantic.html","group":"Colors","viewport":"700x190","subtitle":"Success / warning / danger / info","name":"Semantic Colors"},{"path":"preview/color-text.html","group":"Colors","viewport":"700x200","subtitle":"Foreground on light & dark surfaces","name":"Text Colors"},{"path":"preview/comp-badges.html","group":"Components","viewport":"700x205","subtitle":"Status badges and selectable chips","name":"Badges & Chips"},{"path":"preview/comp-buttons.html","group":"Components","viewport":"700x205","subtitle":"White text on green; primary, secondary, outline, ghost + sizes","name":"Buttons"},{"path":"preview/comp-cards.html","group":"Components","viewport":"700x250","subtitle":"Surface + elevated variants","name":"Service Cards"},{"path":"preview/comp-forms.html","group":"Components","viewport":"700x340","subtitle":"Input, select, textarea, focus state","name":"Form Fields"},{"path":"preview/radii.html","group":"Spacing","viewport":"700x190","subtitle":"8 → pill","name":"Corner Radii"},{"path":"preview/shadows.html","group":"Spacing","viewport":"700x255","subtitle":"Soft teal-tinted shadow scale","name":"Elevation / Shadows"},{"path":"preview/spacing.html","group":"Spacing","viewport":"700x230","subtitle":"4-pt base grid tokens","name":"Spacing Scale"},{"path":"preview/type-body.html","group":"Type","viewport":"700x230","subtitle":"Lead, body, small, caption","name":"Body & Caption"},{"path":"preview/type-display.html","group":"Type","viewport":"700x215","subtitle":"Bricolage Grotesque 800","name":"Display Type"},{"path":"preview/type-families.html","group":"Type","viewport":"700x205","subtitle":"Bricolage Grotesque + Plus Jakarta Sans","name":"Type Families"},{"path":"preview/type-headings.html","group":"Type","viewport":"700x285","subtitle":"H1–H4 specimens","name":"Headings"},{"path":"preview/type-scale.html","group":"Type","viewport":"700x320","subtitle":"Modular size ladder","name":"Type Scale"}],"globalCssPaths":["styles.css"],"tokens":[],"themes":[],"fonts":[],"brandFonts":[],"source":"spa"}